imagespec_fast_builder/__init__.py
imagespec_fast_builder/_image_builder.py
imagespec_fast_builder-0.0.33.dist-info/METADATA
imagespec_fast_builder-0.0.33.dist-info/WHEEL
imagespec_fast_builder-0.0.33.dist-info/entry_points.txt
imagespec_fast_builder-0.0.33.dist-info/licenses/LICENSE
imagespec_fast_builder-0.0.33.dist-info/RECORD
