Metadata-Version: 2.3
Name: imagespec-fast-builder
Version: 0.0.33
Summary: A faster ImageSpec builder for flytekit
Project-URL: Issues, https://github.com/thomasjpfan/imagespec-fast-builder/issues
Project-URL: Source, https://github.com/thomasjpfan/imagespec-fast-builder
Author-email: "Thomas J. Fan" <thomasjpfan@gmail.com>
License-Expression: MIT
License-File: LICENSE
Classifier: Development Status :: 4 - Beta
Classifier: Programming Language :: Python
Classifier: Programming Language :: Python :: 3.8
Classifier: Programming Language :: Python :: 3.9
Classifier: Programming Language :: Python :: 3.10
Classifier: Programming Language :: Python :: 3.11
Classifier: Programming Language :: Python :: 3.12
Classifier: Programming Language :: Python :: Implementation :: CPython
Classifier: Programming Language :: Python :: Implementation :: PyPy
Requires-Python: >=3.8
Requires-Dist: flytekit>=1.11.0
